zyl_utils/__init__.py
zyl_utils/test_utils.py
zyl_utils/api_utils/__init__.py
zyl_utils/api_utils/api_utils.py
zyl_utils/api_utils/test_api.py
zyl_utils/data_utils/Analysis.py
zyl_utils/data_utils/Analyzer.py
zyl_utils/data_utils/__init__.py
zyl_utils/data_utils/analysis.py
zyl_utils/data_utils/collection.py
zyl_utils/data_utils/html_processing.py
zyl_utils/data_utils/image_processing.py
zyl_utils/data_utils/image_utils.py
zyl_utils/data_utils/nlp_utils.py
zyl_utils/data_utils/pdf_processing.py
zyl_utils/data_utils/preparation.py
zyl_utils/data_utils/preprocessing.py
zyl_utils/data_utils/processing.py
zyl_utils/data_utils/text_processing.py
zyl_utils/data_utils/utils.py
zyl_utils/model_utils/DDPT5model.py
zyl_utils/model_utils/__init__.py
zyl_utils/model_utils/entry_match.py
zyl_utils/model_utils/model_utils.py
zyl_utils/model_utils/my_T5model.py
zyl_utils/model_utils/my_model.py
zyl_utils/model_utils/ner_model.py
zyl_utils/model_utils/ner_utils.py
zyl_utils/model_utils/algorithms/__init__.py
zyl_utils/model_utils/algorithms/sunday_match.py
zyl_utils/model_utils/metrics/__init__.py
zyl_utils/model_utils/metrics/ner_metric.py
zyl_utils/model_utils/models/DDPT5model.py
zyl_utils/model_utils/models/__init__.py
zyl_utils/model_utils/models/entry_match.py
zyl_utils/model_utils/models/model_utils.py
zyl_utils/model_utils/models/my_T5model.py
zyl_utils/model_utils/models/my_model.py
zyl_utils/model_utils/models/ner_bio.py
zyl_utils/model_utils/models/ner_model.py
zyl_utils/model_utils/models/ner_t5.py
zyl_utils/model_utils/models/re_ranker_cross_encoder.py
zyl_utils/model_utils/models/reranker_cross_encoder.py
zyl_utils/model_utils/models/retrieval_bi_encoder.py
zyl_utils/model_utils/models/utils.py
zyl_utils/others/__init__.py
zyl_utils/others/others.py
zyl_utils-0.1.4.dist-info/METADATA
zyl_utils-0.1.4.dist-info/WHEEL
zyl_utils-0.1.4.dist-info/top_level.txt
zyl_utils-0.1.4.dist-info/RECORD
