Metadata-Version: 2.1
Name: zyl-utils
Version: 0.1.4
Summary: optimizer
Home-page: https://github.com/ZYuliang/zyl-utils
Author: zyl
Author-email: 1137379695@qq.com
Maintainer: zyl
Maintainer-email: 1137379695@qq.com
License: UNKNOWN
Platform: all
Classifier: Programming Language :: Python :: 3
Classifier: License :: OSI Approved :: MIT License
Classifier: Operating System :: OS Independent
Requires-Dist: tqdm
Requires-Dist: transformers
Requires-Dist: torch
Requires-Dist: wandb
Requires-Dist: loguru
Requires-Dist: langid
Requires-Dist: matplotlib
Requires-Dist: numpy
Requires-Dist: pandas
Requires-Dist: typing
Requires-Dist: simpletransformers
